meta_scraper/__init__.py
meta_scraper/client.py
meta_scraper/utils.py
meta_scraper-0.0.1.dist-info/LICENSE
meta_scraper-0.0.1.dist-info/METADATA
meta_scraper-0.0.1.dist-info/WHEEL
meta_scraper-0.0.1.dist-info/top_level.txt
meta_scraper-0.0.1.dist-info/RECORD
