Metadata-Version: 2.1
Name: meta-scraper
Version: 0.0.1
Summary: Facebook (Meta) Scraper
Home-page: https://github.com/meta-scraper/facebook-scraper-python
Author: meta-scraper
Author-email: michael63s@protonmail.com
License: MIT
Keywords: facebook meta pages reviews api sdk scraper parser extractor
Platform: UNKNOWN
Classifier: Programming Language :: Python
Classifier: License :: OSI Approved :: MIT License
Classifier: Operating System :: OS Independent
Classifier: Intended Audience :: Developers
Classifier: Topic :: Utilities
License-File: LICENSE
Requires-Dist: requests
